di_container/__init__.py
di_container/container.py
di_container/enums.py
di_container/exceptions.py
di_container/fastapi_integration.py
di_container/registration.py
di_container/service_provider.py
di_done_right-1.0.1.dist-info/licenses/LICENSE
di_done_right-1.0.1.dist-info/METADATA
di_done_right-1.0.1.dist-info/WHEEL
di_done_right-1.0.1.dist-info/top_level.txt
di_done_right-1.0.1.dist-info/RECORD
