Metadata-Version: 2.4
Name: di-done-right
Version: 1.0.1
Summary: A modern dependency injection framework for Python inspired by .NET DI
Author-email: Tom Lazelle <tomlazelle@yahoo.com>
License: MIT License
Project-URL: homepage, https://github.com/tomlazelle/di_done_right
Project-URL: repository, https://github.com/tomlazelle/di_done_right
Project-URL: documentation, https://github.com/tomlazelle/di_done_right#documentation
Keywords: dependency-injection,di,ioc,inversion-of-control,dotnet,fastapi
Classifier: Development Status :: 5 - Production/Stable
Classifier: Intended Audience :: Developers
Classifier: License :: OSI Approved :: MIT License
Classifier: Operating System :: OS Independent
Classifier: Programming Language :: Python :: 3
Classifier: Programming Language :: Python :: 3.9
Classifier: Programming Language :: Python :: 3.10
Classifier: Programming Language :: Python :: 3.11
Classifier: Programming Language :: Python :: 3.12
Classifier: Programming Language :: Python :: 3.13
Classifier: Topic :: Software Development :: Libraries :: Python Modules
Classifier: Topic :: Software Development :: Libraries
Classifier: Topic :: Internet :: WWW/HTTP :: HTTP Servers
Classifier: Topic :: Internet :: WWW/HTTP :: Dynamic Content
Classifier: Typing :: Typed
Requires-Python: >=3.9
License-File: LICENSE
Provides-Extra: dev
Requires-Dist: pytest>=7.0; extra == "dev"
Requires-Dist: pytest-cov>=4.0; extra == "dev"
Requires-Dist: mypy>=1.0; extra == "dev"
Requires-Dist: black>=22.0; extra == "dev"
Requires-Dist: isort>=5.0; extra == "dev"
Requires-Dist: flake8>=4.0; extra == "dev"
Provides-Extra: fastapi
Requires-Dist: fastapi>=0.100.0; extra == "fastapi"
Requires-Dist: uvicorn>=0.20.0; extra == "fastapi"
Dynamic: license-file
